dbt2lookml/__init__.py
dbt2lookml/cli.py
dbt2lookml/enums.py
dbt2lookml/exceptions.py
dbt2lookml/generators/__init__.py
dbt2lookml/generators/dimension.py
dbt2lookml/generators/explore.py
dbt2lookml/generators/measure.py
dbt2lookml/generators/utils.py
dbt2lookml/generators/view.py
dbt2lookml/models/__init__.py
dbt2lookml/models/dbt.py
dbt2lookml/models/looker.py
dbt2lookml/models/schema.py
dbt2lookml/parsers/__init__.py
dbt2lookml/parsers/base.py
dbt2lookml/parsers/catalog.py
dbt2lookml/parsers/exposure.py
dbt2lookml/parsers/model.py
dbt2lookml/utils.py
dbt2lookml-0.2.4.dist-info/LICENSE
dbt2lookml-0.2.4.dist-info/METADATA
dbt2lookml-0.2.4.dist-info/WHEEL
dbt2lookml-0.2.4.dist-info/entry_points.txt
dbt2lookml-0.2.4.dist-info/RECORD
