Metadata-Version: 2.1
Name: dbt2lookml
Version: 0.2.4
Summary: Generate lookml views from bigquery via dbt models
Home-page: https://github.com/magnus-ffcg/dbt2lookml
Requires-Python: >=3.9.0,<4.0
Classifier: Programming Language :: Python :: 3
Classifier: Programming Language :: Python :: 3.9
Classifier: Programming Language :: Python :: 3.10
Classifier: Programming Language :: Python :: 3.11
Classifier: Programming Language :: Python :: 3.12
Classifier: Programming Language :: Python :: 3.13
Requires-Dist: PyYAML (>=5.0)
Requires-Dist: datamodel-code-generator (>=0.26.3,<0.27.0)
Requires-Dist: importlib-metadata (>=4)
Requires-Dist: lkml (>=1.1)
Requires-Dist: pydantic (>=2.9)
Requires-Dist: pytest-mock (>=3.14.0,<4.0.0)
Requires-Dist: rich (>=13.9.4)
Requires-Dist: typing-extensions (>=4.0)
Requires-Dist: unidecode (>=1.3.0)
Project-URL: Repository, https://github.com/magnus-ffcg/dbt2lookml
